PyIRCIoT/ChangeLog
PyIRCIoT/LICENSE
PyIRCIoT/LICENSE-de.txt
PyIRCIoT/LICENSE-ru.txt
PyIRCIoT/TODO.txt
PyIRCIoT/__init__.py
PyIRCIoT/irciot.py
PyIRCIoT/irciot_errors.py
PyIRCIoT/irciot_router.py
PyIRCIoT/irciot_shared.py
PyIRCIoT/languages.py
PyIRCIoT/ldict.json
PyIRCIoT/rfc1459.py
PyIRCIoT/rfc2217.py
PyIRCIoT/udpbrcst.py
PyIRCIoT/esp8266/README.txt
PyIRCIoT/esp8266/irciotmini.py
PyIRCIoT/esp8266/main-linux.py
PyIRCIoT/esp8266/main-relay.py
PyIRCIoT/esp8266/main.py
PyIRCIoT/esp8266/rfc1459mini.py
PyIRCIoT/esp8266/udpbrcstmini.py
PyIRCIoT/examples/defrag.py
PyIRCIoT/examples/elpy.py
PyIRCIoT/examples/iotbot.py
PyIRCIoT/examples/proxy.py
PyIRCIoT/examples/router.py
PyIRCIoT/examples/udpbot.py
PyIRCIoT/iimakecert/iimakecert.sh
PyIRCIoT/services/CRS.py
PyIRCIoT/services/FUS.py
PyIRCIoT/services/GDS.py
PyIRCIoT/services/GRS.py
PyIRCIoT/services/GTS.py
PyIRCIoT/services/HIS.py
PyIRCIoT/techdoc/joints.txt
PyIRCIoT/testing/auto-irciot.sh
PyIRCIoT/testing/irciot-test.py
PyIRCIoT/testing/irciot.py
PyIRCIoT/testing/irciot_router-test.py
PyIRCIoT/testing/irciot_router.py
PyIRCIoT/testing/languages-test.py
PyIRCIoT/testing/languages.py
PyIRCIoT/testing/rfc1459-test.py
PyIRCIoT/testing/rfc1459.py
PyIRCIoT/testing/rfc2217.py
PyIRCIoT/testing/udpbrcst-test.py
PyIRCIoT/testing/udpbrcst.py
PyIRCIoT-0.0.229.dist-info/LICENSE.txt
PyIRCIoT-0.0.229.dist-info/METADATA
PyIRCIoT-0.0.229.dist-info/WHEEL
PyIRCIoT-0.0.229.dist-info/top_level.txt
PyIRCIoT-0.0.229.dist-info/RECORD
